[{"class":"Organization","view":{"query":"select * from a1390629227_0"},"identifier":[{"path":"Organization","column":["_subject"]}],"mapping":[{"path":"Organization.id","function":"return 'example-organization-2'"},{"path":"Organization.meta.profile[0]","column":["a2"]},{"path":"Organization.text.status","column":["a3"]},{"path":"Organization.text.div","column":["a4"]},{"path":"Organization.identifier[0].system","column":["a5"]},{"path":"Organization.identifier[0].value","column":["a6"]},{"path":"Organization.identifier[1].system","column":["a7"]},{"path":"Organization.identifier[1].value","column":["a8"]},{"path":"Organization.active","column":["a9"]},{"path":"Organization.type[0].coding[0].system","column":["a10"]},{"path":"Organization.type[0].coding[0].code","column":["a11"]},{"path":"Organization.type[0].coding[0].display","column":["a12"]},{"path":"Organization.name","column":["a13"]},{"path":"Organization.telecom[0].system","column":["a14"]},{"path":"Organization.telecom[0].value","column":["a15"]},{"path":"Organization.telecom[1].system","column":["a16"]},{"path":"Organization.telecom[1].value","column":["a17"]},{"path":"Organization.address[0].line[0]","column":["a18"]},{"path":"Organization.address[0].city","column":["a19"]},{"path":"Organization.address[0].state","function":"return getValue('a20').upper()","column":["a20"]},{"path":"Organization.address[0].postalCode","column":["a21"]},{"path":"Organization.address[0].country","function":"return getValue('a22').upper()","column":["a22"]}]}]