[{"class":"Claim","view":{"query":"select * from a1788935534_0"},"identifier":[{"path":"Claim","column":["_subject"]}],"mapping":[{"path":"Claim.id","function":"return '100155'"},{"path":"Claim.text.status","column":["a2"]},{"path":"Claim.text.div","column":["a3"]},{"path":"Claim.contained{Patient}[0].id","column":["a4"]},{"path":"Claim.contained{Patient}[0].name[0].use","column":["a5"]},{"path":"Claim.contained{Patient}[0].name[0].family","column":["a6"]},{"path":"Claim.contained{Patient}[0].name[0].given[0]","column":["a7"]},{"path":"Claim.contained{Patient}[0].gender","column":["a8"]},{"path":"Claim.contained{Patient}[0].birthDate","column":["a9"]},{"path":"Claim.contained{Patient}[0].address[0].use","column":["a10"]},{"path":"Claim.contained{Patient}[0].address[0].line[0]","column":["a11"]},{"path":"Claim.contained{Patient}[0].address[0].city","column":["a12"]},{"path":"Claim.contained{Patient}[0].address[0].postalCode","column":["a13"]},{"path":"Claim.contained{Patient}[0].address[0].country","function":"return getValue('a14').upper()","column":["a14"]},{"path":"Claim.identifier[0].system","column":["a15"]},{"path":"Claim.identifier[0].value","column":["a16"]},{"path":"Claim.status","column":["a17"]},{"path":"Claim.type.coding[0].system","column":["a18"]},{"path":"Claim.type.coding[0].code","column":["a19"]},{"path":"Claim.use","column":["a20"]},{"path":"Claim.patient.reference","column":["a21"]},{"path":"Claim.created","column":["a22"]},{"path":"Claim.insurer.identifier.system","column":["a23"]},{"path":"Claim.insurer.identifier.value","column":["a24"]},{"path":"Claim.provider.identifier.system","column":["a25"]},{"path":"Claim.provider.identifier.value","column":["a26"]},{"path":"Claim.priority.coding[0].code","column":["a27"]},{"path":"Claim.payee.type.coding[0].code","column":["a28"]},{"path":"Claim.careTeam[0].sequence","column":["a29"]},{"path":"Claim.careTeam[0].provider.identifier.system","column":["a30"]},{"path":"Claim.careTeam[0].provider.identifier.value","column":["a31"]},{"path":"Claim.diagnosis[0].sequence","column":["a32"]},{"path":"Claim.diagnosis[0].diagnosisCodeableConcept.coding[0].code","column":["a33"]},{"path":"Claim.insurance[0].sequence","column":["a34"]},{"path":"Claim.insurance[0].focal","column":["a35"]},{"path":"Claim.insurance[0].coverage.reference","column":["a36"]},{"path":"Claim.item[0].sequence","column":["a37"]},{"path":"Claim.item[0].careTeamSequence[0]","column":["a38"]},{"path":"Claim.item[0].productOrService.coding[0].code","column":["a39"]},{"path":"Claim.item[0].servicedDate","column":["a40"]},{"path":"Claim.item[0].unitPrice.value","column":["a41"]},{"path":"Claim.item[0].unitPrice.currency","function":"return getValue('a42').upper()","column":["a42"]},{"path":"Claim.item[0].net.value","column":["a43"]},{"path":"Claim.item[0].net.currency","function":"return getValue('a44').upper()","column":["a44"]},{"path":"Claim.meta.tag[0].system","column":["a45"]},{"path":"Claim.meta.tag[0].code","function":"return getValue('a46').upper()","column":["a46"]},{"path":"Claim.meta.tag[0].display","column":["a47"]}]}]