[{"class":"StructureDefinition","view":{"tableName":"a145713959_0"},"identifier":[{"path":"StructureDefinition","column":["_subject"]}],"mapping":[{"path":"StructureDefinition.id","function":"return 'DeviceUseStatement'"},{"path":"StructureDefinition.meta.lastUpdated","column":["a2"]},{"path":"StructureDefinition.text.status","column":["a3"]},{"path":"StructureDefinition.text.div","column":["a4"]},{"path":"StructureDefinition.extension[0].url","column":["a5"]},{"path":"StructureDefinition.extension[0].valueString","column":["a6"]},{"path":"StructureDefinition.extension[1].url","column":["a7"]},{"path":"StructureDefinition.extension[1].valueCode","column":["a8"]},{"path":"StructureDefinition.extension[2].url","column":["a9"]},{"path":"StructureDefinition.extension[2].valueInteger","column":["a10"]},{"path":"StructureDefinition.extension[3].url","column":["a11"]},{"path":"StructureDefinition.extension[3].valueCode","column":["a12"]},{"path":"StructureDefinition.extension[4].url","column":["a13"]},{"path":"StructureDefinition.extension[4].valueCode","column":["a14"]},{"path":"StructureDefinition.url","column":["a15"]},{"path":"StructureDefinition.version","column":["a16"]},{"path":"StructureDefinition.name","column":["a17"]},{"path":"StructureDefinition.status","column":["a18"]},{"path":"StructureDefinition.date","column":["a19"]},{"path":"StructureDefinition.publisher","column":["a20"]},{"path":"StructureDefinition.contact[0].telecom[0].system","column":["a21"]},{"path":"StructureDefinition.contact[0].telecom[0].value","column":["a22"]},{"path":"StructureDefinition.contact[1].telecom[0].system","column":["a23"]},{"path":"StructureDefinition.contact[1].telecom[0].value","column":["a24"]},{"path":"StructureDefinition.description","column":["a25"]},{"path":"StructureDefinition.fhirVersion","column":["a26"]},{"path":"StructureDefinition.mapping[0].identity","column":["a27"]},{"path":"StructureDefinition.mapping[0].uri","column":["a28"]},{"path":"StructureDefinition.mapping[0].name","column":["a29"]},{"path":"StructureDefinition.mapping[1].identity","column":["a30"]},{"path":"StructureDefinition.mapping[1].uri","column":["a31"]},{"path":"StructureDefinition.mapping[1].name","column":["a32"]},{"path":"StructureDefinition.mapping[2].identity","column":["a33"]},{"path":"StructureDefinition.mapping[2].uri","column":["a34"]},{"path":"StructureDefinition.mapping[2].name","column":["a35"]},{"path":"StructureDefinition.mapping[3].identity","column":["a36"]},{"path":"StructureDefinition.mapping[3].uri","column":["a37"]},{"path":"StructureDefinition.mapping[3].name","column":["a38"]},{"path":"StructureDefinition.mapping[4].identity","column":["a39"]},{"path":"StructureDefinition.mapping[4].uri","column":["a40"]},{"path":"StructureDefinition.mapping[4].name","column":["a41"]},{"path":"StructureDefinition.kind","column":["a42"]},{"path":"StructureDefinition.abstract","column":["a43"]},{"path":"StructureDefinition.type","column":["a44"]},{"path":"StructureDefinition.baseDefinition","column":["a45"]},{"path":"StructureDefinition.derivation","column":["a46"]},{"path":"StructureDefinition.snapshot.element[0].id","column":["a47"]},{"path":"StructureDefinition.snapshot.element[0].path","column":["a48"]},{"path":"StructureDefinition.snapshot.element[0].short","column":["a49"]},{"path":"StructureDefinition.snapshot.element[0].definition","column":["a50"]},{"path":"StructureDefinition.snapshot.element[0].min","column":["a51"]},{"path":"StructureDefinition.snapshot.element[0].max","column":["a52"]},{"path":"StructureDefinition.snapshot.element[0].base.path","column":["a53"]},{"path":"StructureDefinition.snapshot.element[0].base.min","column":["a54"]},{"path":"StructureDefinition.snapshot.element[0].base.max","column":["a55"]},{"path":"StructureDefinition.snapshot.element[0].constraint[0].key","column":["a56"]},{"path":"StructureDefinition.snapshot.element[0].constraint[0].severity","column":["a57"]},{"path":"StructureDefinition.snapshot.element[0].constraint[0].human","column":["a58"]},{"path":"StructureDefinition.snapshot.element[0].constraint[0].expression","column":["a59"]},{"path":"StructureDefinition.snapshot.element[0].constraint[0].xpath","column":["a60"]},{"path":"StructureDefinition.snapshot.element[0].constraint[0].source","column":["a61"]},{"path":"StructureDefinition.snapshot.element[0].constraint[1].key","column":["a62"]},{"path":"StructureDefinition.snapshot.element[0].constraint[1].severity","column":["a63"]},{"path":"StructureDefinition.snapshot.element[0].constraint[1].human","column":["a64"]},{"path":"StructureDefinition.snapshot.element[0].constraint[1].expression","column":["a65"]},{"path":"StructureDefinition.snapshot.element[0].constraint[1].xpath","column":["a66"]},{"path":"StructureDefinition.snapshot.element[0].constraint[1].source","column":["a67"]},{"path":"StructureDefinition.snapshot.element[0].constraint[2].key","column":["a68"]},{"path":"StructureDefinition.snapshot.element[0].constraint[2].severity","column":["a69"]},{"path":"StructureDefinition.snapshot.element[0].constraint[2].human","column":["a70"]},{"path":"StructureDefinition.snapshot.element[0].constraint[2].expression","column":["a71"]},{"path":"StructureDefinition.snapshot.element[0].constraint[2].xpath","column":["a72"]},{"path":"StructureDefinition.snapshot.element[0].constraint[2].source","column":["a73"]},{"path":"StructureDefinition.snapshot.element[0].constraint[3].key","column":["a74"]},{"path":"StructureDefinition.snapshot.element[0].constraint[3].severity","column":["a75"]},{"path":"StructureDefinition.snapshot.element[0].constraint[3].human","column":["a76"]},{"path":"StructureDefinition.snapshot.element[0].constraint[3].expression","column":["a77"]},{"path":"StructureDefinition.snapshot.element[0].constraint[3].xpath","column":["a78"]},{"path":"StructureDefinition.snapshot.element[0].constraint[3].source","column":["a79"]},{"path":"StructureDefinition.snapshot.element[0].constraint[4].extension[0].url","column":["a80"]},{"path":"StructureDefinition.snapshot.element[0].constraint[4].extension[0].valueBoolean","column":["a81"]},{"path":"StructureDefinition.snapshot.element[0].constraint[4].extension[1].url","column":["a82"]},{"path":"StructureDefinition.snapshot.element[0].constraint[4].extension[1].valueMarkdown","column":["a83"]},{"path":"StructureDefinition.snapshot.element[0].constraint[4].key","column":["a84"]},{"path":"StructureDefinition.snapshot.element[0].constraint[4].severity","column":["a85"]},{"path":"StructureDefinition.snapshot.element[0].constraint[4].human","column":["a86"]},{"path":"StructureDefinition.snapshot.element[0].constraint[4].expression","column":["a87"]},{"path":"StructureDefinition.snapshot.element[0].constraint[4].xpath","column":["a88"]},{"path":"StructureDefinition.snapshot.element[0].constraint[4].source","column":["a89"]},{"path":"StructureDefinition.snapshot.element[0].isModifier","column":["a90"]},{"path":"StructureDefinition.snapshot.element[0].isSummary","column":["a91"]},{"path":"StructureDefinition.snapshot.element[0].mapping[0].identity","column":["a92"]},{"path":"StructureDefinition.snapshot.element[0].mapping[0].map","column":["a93"]},{"path":"StructureDefinition.snapshot.element[0].mapping[1].identity","column":["a94"]},{"path":"StructureDefinition.snapshot.element[0].mapping[1].map","column":["a95"]},{"path":"StructureDefinition.snapshot.element[0].mapping[2].identity","column":["a96"]},{"path":"StructureDefinition.snapshot.element[0].mapping[2].map","column":["a97"]},{"path":"StructureDefinition.snapshot.element[1].id","column":["a98"]},{"path":"StructureDefinition.snapshot.element[1].path","column":["a99"]},{"path":"StructureDefinition.snapshot.element[1].short","column":["a100"]},{"path":"StructureDefinition.snapshot.element[1].definition","column":["a101"]},{"path":"StructureDefinition.snapshot.element[1].comment","column":["a102"]},{"path":"StructureDefinition.snapshot.element[1].min","column":["a103"]},{"path":"StructureDefinition.snapshot.element[1].max","column":["a104"]},{"path":"StructureDefinition.snapshot.element[1].base.path","column":["a105"]},{"path":"StructureDefinition.snapshot.element[1].base.min","column":["a106"]},{"path":"StructureDefinition.snapshot.element[1].base.max","column":["a107"]},{"path":"StructureDefinition.snapshot.element[1].type[0].extension[0].url","column":["a108"]},{"path":"StructureDefinition.snapshot.element[1].type[0].extension[0].valueUrl","column":["a109"]},{"path":"StructureDefinition.snapshot.element[1].type[0].code","column":["a110"]},{"path":"StructureDefinition.snapshot.element[1].isModifier","column":["a111"]},{"path":"StructureDefinition.snapshot.element[1].isSummary","column":["a112"]},{"path":"StructureDefinition.snapshot.element[2].id","column":["a113"]},{"path":"StructureDefinition.snapshot.element[2].path","column":["a114"]},{"path":"StructureDefinition.snapshot.element[2].short","column":["a115"]},{"path":"StructureDefinition.snapshot.element[2].definition","column":["a116"]},{"path":"StructureDefinition.snapshot.element[2].min","column":["a117"]},{"path":"StructureDefinition.snapshot.element[2].max","column":["a118"]},{"path":"StructureDefinition.snapshot.element[2].base.path","column":["a119"]},{"path":"StructureDefinition.snapshot.element[2].base.min","column":["a120"]},{"path":"StructureDefinition.snapshot.element[2].base.max","column":["a121"]},{"path":"StructureDefinition.snapshot.element[2].type[0].code","column":["a122"]},{"path":"StructureDefinition.snapshot.element[2].constraint[0].key","column":["a123"]},{"path":"StructureDefinition.snapshot.element[2].constraint[0].severity","column":["a124"]},{"path":"StructureDefinition.snapshot.element[2].constraint[0].human","column":["a125"]},{"path":"StructureDefinition.snapshot.element[2].constraint[0].expression","column":["a126"]},{"path":"StructureDefinition.snapshot.element[2].constraint[0].xpath","column":["a127"]},{"path":"StructureDefinition.snapshot.element[2].constraint[0].source","column":["a128"]},{"path":"StructureDefinition.snapshot.element[2].isModifier","column":["a129"]},{"path":"StructureDefinition.snapshot.element[2].isSummary","column":["a130"]},{"path":"StructureDefinition.snapshot.element[3].id","column":["a131"]},{"path":"StructureDefinition.snapshot.element[3].path","column":["a132"]},{"path":"StructureDefinition.snapshot.element[3].short","column":["a133"]},{"path":"StructureDefinition.snapshot.element[3].definition","column":["a134"]},{"path":"StructureDefinition.snapshot.element[3].comment","column":["a135"]},{"path":"StructureDefinition.snapshot.element[3].min","column":["a136"]},{"path":"StructureDefinition.snapshot.element[3].max","column":["a137"]},{"path":"StructureDefinition.snapshot.element[3].base.path","column":["a138"]},{"path":"StructureDefinition.snapshot.element[3].base.min","column":["a139"]},{"path":"StructureDefinition.snapshot.element[3].base.max","column":["a140"]},{"path":"StructureDefinition.snapshot.element[3].type[0].code","column":["a141"]},{"path":"StructureDefinition.snapshot.element[3].constraint[0].key","column":["a142"]},{"path":"StructureDefinition.snapshot.element[3].constraint[0].severity","column":["a143"]},{"path":"StructureDefinition.snapshot.element[3].constraint[0].human","column":["a144"]},{"path":"StructureDefinition.snapshot.element[3].constraint[0].expression","column":["a145"]},{"path":"StructureDefinition.snapshot.element[3].constraint[0].xpath","column":["a146"]},{"path":"StructureDefinition.snapshot.element[3].constraint[0].source","column":["a147"]},{"path":"StructureDefinition.snapshot.element[3].isModifier","column":["a148"]},{"path":"StructureDefinition.snapshot.element[3].isModifierReason","column":["a149"]}]},{"class":"StructureDefinition","view":{"tableName":"a145713959_1"},"identifier":[{"path":"StructureDefinition","column":["_subject"]}],"mapping":[{"path":"StructureDefinition.snapshot.element[3].isSummary","column":["a1"]},{"path":"StructureDefinition.snapshot.element[4].id","column":["a2"]},{"path":"StructureDefinition.snapshot.element[4].path","column":["a3"]},{"path":"StructureDefinition.snapshot.element[4].short","column":["a4"]},{"path":"StructureDefinition.snapshot.element[4].definition","column":["a5"]},{"path":"StructureDefinition.snapshot.element[4].comment","column":["a6"]},{"path":"StructureDefinition.snapshot.element[4].min","column":["a7"]},{"path":"StructureDefinition.snapshot.element[4].max","column":["a8"]},{"path":"StructureDefinition.snapshot.element[4].base.path","column":["a9"]},{"path":"StructureDefinition.snapshot.element[4].base.min","column":["a10"]},{"path":"StructureDefinition.snapshot.element[4].base.max","column":["a11"]},{"path":"StructureDefinition.snapshot.element[4].type[0].code","column":["a12"]},{"path":"StructureDefinition.snapshot.element[4].constraint[0].key","column":["a13"]},{"path":"StructureDefinition.snapshot.element[4].constraint[0].severity","column":["a14"]},{"path":"StructureDefinition.snapshot.element[4].constraint[0].human","column":["a15"]},{"path":"StructureDefinition.snapshot.element[4].constraint[0].expression","column":["a16"]},{"path":"StructureDefinition.snapshot.element[4].constraint[0].xpath","column":["a17"]},{"path":"StructureDefinition.snapshot.element[4].constraint[0].source","column":["a18"]},{"path":"StructureDefinition.snapshot.element[4].isModifier","column":["a19"]},{"path":"StructureDefinition.snapshot.element[4].isSummary","column":["a20"]},{"path":"StructureDefinition.snapshot.element[4].binding.extension[0].url","column":["a21"]},{"path":"StructureDefinition.snapshot.element[4].binding.extension[0].valueCanonical","column":["a22"]},{"path":"StructureDefinition.snapshot.element[4].binding.extension[1].url","column":["a23"]},{"path":"StructureDefinition.snapshot.element[4].binding.extension[1].valueString","column":["a24"]},{"path":"StructureDefinition.snapshot.element[4].binding.extension[2].url","column":["a25"]},{"path":"StructureDefinition.snapshot.element[4].binding.extension[2].valueBoolean","column":["a26"]},{"path":"StructureDefinition.snapshot.element[4].binding.strength","column":["a27"]},{"path":"StructureDefinition.snapshot.element[4].binding.description","column":["a28"]},{"path":"StructureDefinition.snapshot.element[4].binding.valueSet","column":["a29"]},{"path":"StructureDefinition.snapshot.element[5].id","column":["a30"]},{"path":"StructureDefinition.snapshot.element[5].path","column":["a31"]},{"path":"StructureDefinition.snapshot.element[5].short","column":["a32"]},{"path":"StructureDefinition.snapshot.element[5].definition","column":["a33"]},{"path":"StructureDefinition.snapshot.element[5].comment","column":["a34"]},{"path":"StructureDefinition.snapshot.element[5].alias[0]","column":["a35"]},{"path":"StructureDefinition.snapshot.element[5].alias[1]","column":["a36"]},{"path":"StructureDefinition.snapshot.element[5].alias[2]","column":["a37"]},{"path":"StructureDefinition.snapshot.element[5].alias[3]","column":["a38"]},{"path":"StructureDefinition.snapshot.element[5].min","column":["a39"]},{"path":"StructureDefinition.snapshot.element[5].max","column":["a40"]},{"path":"StructureDefinition.snapshot.element[5].base.path","column":["a41"]},{"path":"StructureDefinition.snapshot.element[5].base.min","column":["a42"]},{"path":"StructureDefinition.snapshot.element[5].base.max","column":["a43"]},{"path":"StructureDefinition.snapshot.element[5].type[0].code","column":["a44"]},{"path":"StructureDefinition.snapshot.element[5].constraint[0].key","column":["a45"]},{"path":"StructureDefinition.snapshot.element[5].constraint[0].severity","column":["a46"]},{"path":"StructureDefinition.snapshot.element[5].constraint[0].human","column":["a47"]},{"path":"StructureDefinition.snapshot.element[5].constraint[0].expression","column":["a48"]},{"path":"StructureDefinition.snapshot.element[5].constraint[0].xpath","column":["a49"]},{"path":"StructureDefinition.snapshot.element[5].constraint[0].source","column":["a50"]},{"path":"StructureDefinition.snapshot.element[5].isModifier","column":["a51"]},{"path":"StructureDefinition.snapshot.element[5].isSummary","column":["a52"]},{"path":"StructureDefinition.snapshot.element[5].mapping[0].identity","column":["a53"]},{"path":"StructureDefinition.snapshot.element[5].mapping[0].map","column":["a54"]},{"path":"StructureDefinition.snapshot.element[6].id","column":["a55"]},{"path":"StructureDefinition.snapshot.element[6].path","column":["a56"]},{"path":"StructureDefinition.snapshot.element[6].short","column":["a57"]},{"path":"StructureDefinition.snapshot.element[6].definition","column":["a58"]},{"path":"StructureDefinition.snapshot.element[6].comment","column":["a59"]},{"path":"StructureDefinition.snapshot.element[6].alias[0]","column":["a60"]},{"path":"StructureDefinition.snapshot.element[6].alias[1]","column":["a61"]},{"path":"StructureDefinition.snapshot.element[6].alias[2]","column":["a62"]},{"path":"StructureDefinition.snapshot.element[6].min","column":["a63"]},{"path":"StructureDefinition.snapshot.element[6].max","column":["a64"]},{"path":"StructureDefinition.snapshot.element[6].base.path","column":["a65"]},{"path":"StructureDefinition.snapshot.element[6].base.min","column":["a66"]},{"path":"StructureDefinition.snapshot.element[6].base.max","column":["a67"]},{"path":"StructureDefinition.snapshot.element[6].type[0].code","column":["a68"]},{"path":"StructureDefinition.snapshot.element[6].isModifier","column":["a69"]},{"path":"StructureDefinition.snapshot.element[6].isSummary","column":["a70"]},{"path":"StructureDefinition.snapshot.element[6].mapping[0].identity","column":["a71"]},{"path":"StructureDefinition.snapshot.element[6].mapping[0].map","column":["a72"]},{"path":"StructureDefinition.snapshot.element[7].id","column":["a73"]},{"path":"StructureDefinition.snapshot.element[7].path","column":["a74"]},{"path":"StructureDefinition.snapshot.element[7].short","column":["a75"]},{"path":"StructureDefinition.snapshot.element[7].definition","column":["a76"]},{"path":"StructureDefinition.snapshot.element[7].comment","column":["a77"]},{"path":"StructureDefinition.snapshot.element[7].alias[0]","column":["a78"]},{"path":"StructureDefinition.snapshot.element[7].alias[1]","column":["a79"]},{"path":"StructureDefinition.snapshot.element[7].min","column":["a80"]},{"path":"StructureDefinition.snapshot.element[7].max","column":["a81"]},{"path":"StructureDefinition.snapshot.element[7].base.path","column":["a82"]},{"path":"StructureDefinition.snapshot.element[7].base.min","column":["a83"]},{"path":"StructureDefinition.snapshot.element[7].base.max","column":["a84"]},{"path":"StructureDefinition.snapshot.element[7].type[0].code","column":["a85"]},{"path":"StructureDefinition.snapshot.element[7].constraint[0].key","column":["a86"]},{"path":"StructureDefinition.snapshot.element[7].constraint[0].severity","column":["a87"]},{"path":"StructureDefinition.snapshot.element[7].constraint[0].human","column":["a88"]},{"path":"StructureDefinition.snapshot.element[7].constraint[0].expression","column":["a89"]},{"path":"StructureDefinition.snapshot.element[7].constraint[0].xpath","column":["a90"]},{"path":"StructureDefinition.snapshot.element[7].constraint[0].source","column":["a91"]},{"path":"StructureDefinition.snapshot.element[7].constraint[1].key","column":["a92"]},{"path":"StructureDefinition.snapshot.element[7].constraint[1].severity","column":["a93"]},{"path":"StructureDefinition.snapshot.element[7].constraint[1].human","column":["a94"]},{"path":"StructureDefinition.snapshot.element[7].constraint[1].expression","column":["a95"]},{"path":"StructureDefinition.snapshot.element[7].constraint[1].xpath","column":["a96"]},{"path":"StructureDefinition.snapshot.element[7].constraint[1].source","column":["a97"]},{"path":"StructureDefinition.snapshot.element[7].isModifier","column":["a98"]},{"path":"StructureDefinition.snapshot.element[7].isSummary","column":["a99"]},{"path":"StructureDefinition.snapshot.element[7].mapping[0].identity","column":["a100"]},{"path":"StructureDefinition.snapshot.element[7].mapping[0].map","column":["a101"]},{"path":"StructureDefinition.snapshot.element[8].id","column":["a102"]},{"path":"StructureDefinition.snapshot.element[8].path","column":["a103"]},{"path":"StructureDefinition.snapshot.element[8].short","column":["a104"]},{"path":"StructureDefinition.snapshot.element[8].definition","column":["a105"]},{"path":"StructureDefinition.snapshot.element[8].comment","column":["a106"]},{"path":"StructureDefinition.snapshot.element[8].requirements","column":["a107"]},{"path":"StructureDefinition.snapshot.element[8].alias[0]","column":["a108"]},{"path":"StructureDefinition.snapshot.element[8].alias[1]","column":["a109"]},{"path":"StructureDefinition.snapshot.element[8].min","column":["a110"]},{"path":"StructureDefinition.snapshot.element[8].max","column":["a111"]},{"path":"StructureDefinition.snapshot.element[8].base.path","column":["a112"]},{"path":"StructureDefinition.snapshot.element[8].base.min","column":["a113"]},{"path":"StructureDefinition.snapshot.element[8].base.max","column":["a114"]},{"path":"StructureDefinition.snapshot.element[8].type[0].code","column":["a115"]},{"path":"StructureDefinition.snapshot.element[8].constraint[0].key","column":["a116"]},{"path":"StructureDefinition.snapshot.element[8].constraint[0].severity","column":["a117"]},{"path":"StructureDefinition.snapshot.element[8].constraint[0].human","column":["a118"]},{"path":"StructureDefinition.snapshot.element[8].constraint[0].expression","column":["a119"]},{"path":"StructureDefinition.snapshot.element[8].constraint[0].xpath","column":["a120"]},{"path":"StructureDefinition.snapshot.element[8].constraint[0].source","column":["a121"]},{"path":"StructureDefinition.snapshot.element[8].constraint[1].key","column":["a122"]},{"path":"StructureDefinition.snapshot.element[8].constraint[1].severity","column":["a123"]},{"path":"StructureDefinition.snapshot.element[8].constraint[1].human","column":["a124"]},{"path":"StructureDefinition.snapshot.element[8].constraint[1].expression","column":["a125"]},{"path":"StructureDefinition.snapshot.element[8].constraint[1].xpath","column":["a126"]},{"path":"StructureDefinition.snapshot.element[8].constraint[1].source","column":["a127"]},{"path":"StructureDefinition.snapshot.element[8].isModifier","column":["a128"]},{"path":"StructureDefinition.snapshot.element[8].isModifierReason","column":["a129"]},{"path":"StructureDefinition.snapshot.element[8].isSummary","column":["a130"]},{"path":"StructureDefinition.snapshot.element[8].mapping[0].identity","column":["a131"]},{"path":"StructureDefinition.snapshot.element[8].mapping[0].map","column":["a132"]},{"path":"StructureDefinition.snapshot.element[9].id","column":["a133"]},{"path":"StructureDefinition.snapshot.element[9].path","column":["a134"]},{"path":"StructureDefinition.snapshot.element[9].short","column":["a135"]},{"path":"StructureDefinition.snapshot.element[9].definition","column":["a136"]},{"path":"StructureDefinition.snapshot.element[9].min","column":["a137"]},{"path":"StructureDefinition.snapshot.element[9].max","column":["a138"]},{"path":"StructureDefinition.snapshot.element[9].base.path","column":["a139"]},{"path":"StructureDefinition.snapshot.element[9].base.min","column":["a140"]},{"path":"StructureDefinition.snapshot.element[9].base.max","column":["a141"]},{"path":"StructureDefinition.snapshot.element[9].type[0].code","column":["a142"]},{"path":"StructureDefinition.snapshot.element[9].constraint[0].key","column":["a143"]},{"path":"StructureDefinition.snapshot.element[9].constraint[0].severity","column":["a144"]},{"path":"StructureDefinition.snapshot.element[9].constraint[0].human","column":["a145"]},{"path":"StructureDefinition.snapshot.element[9].constraint[0].expression","column":["a146"]},{"path":"StructureDefinition.snapshot.element[9].constraint[0].xpath","column":["a147"]},{"path":"StructureDefinition.snapshot.element[9].constraint[0].source","column":["a148"]},{"path":"StructureDefinition.snapshot.element[9].isModifier","column":["a149"]}]},{"class":"StructureDefinition","view":{"tableName":"a145713959_2"},"identifier":[{"path":"StructureDefinition","column":["_subject"]}],"mapping":[{"path":"StructureDefinition.snapshot.element[9].isSummary","column":["a1"]},{"path":"StructureDefinition.snapshot.element[9].mapping[0].identity","column":["a2"]},{"path":"StructureDefinition.snapshot.element[9].mapping[0].map","column":["a3"]},{"path":"StructureDefinition.snapshot.element[9].mapping[1].identity","column":["a4"]},{"path":"StructureDefinition.snapshot.element[9].mapping[1].map","column":["a5"]},{"path":"StructureDefinition.snapshot.element[9].mapping[2].identity","column":["a6"]},{"path":"StructureDefinition.snapshot.element[9].mapping[2].map","column":["a7"]},{"path":"StructureDefinition.snapshot.element[10].id","column":["a8"]},{"path":"StructureDefinition.snapshot.element[10].path","column":["a9"]},{"path":"StructureDefinition.snapshot.element[10].short","column":["a10"]},{"path":"StructureDefinition.snapshot.element[10].definition","column":["a11"]},{"path":"StructureDefinition.snapshot.element[10].requirements","column":["a12"]},{"path":"StructureDefinition.snapshot.element[10].alias[0]","column":["a13"]},{"path":"StructureDefinition.snapshot.element[10].min","column":["a14"]},{"path":"StructureDefinition.snapshot.element[10].max","column":["a15"]},{"path":"StructureDefinition.snapshot.element[10].base.path","column":["a16"]},{"path":"StructureDefinition.snapshot.element[10].base.min","column":["a17"]},{"path":"StructureDefinition.snapshot.element[10].base.max","column":["a18"]},{"path":"StructureDefinition.snapshot.element[10].type[0].code","column":["a19"]},{"path":"StructureDefinition.snapshot.element[10].type[0].targetProfile[0]","column":["a20"]},{"path":"StructureDefinition.snapshot.element[10].constraint[0].key","column":["a21"]},{"path":"StructureDefinition.snapshot.element[10].constraint[0].severity","column":["a22"]},{"path":"StructureDefinition.snapshot.element[10].constraint[0].human","column":["a23"]},{"path":"StructureDefinition.snapshot.element[10].constraint[0].expression","column":["a24"]},{"path":"StructureDefinition.snapshot.element[10].constraint[0].xpath","column":["a25"]},{"path":"StructureDefinition.snapshot.element[10].constraint[0].source","column":["a26"]},{"path":"StructureDefinition.snapshot.element[10].isModifier","column":["a27"]},{"path":"StructureDefinition.snapshot.element[10].isSummary","column":["a28"]},{"path":"StructureDefinition.snapshot.element[10].mapping[0].identity","column":["a29"]},{"path":"StructureDefinition.snapshot.element[10].mapping[0].map","column":["a30"]},{"path":"StructureDefinition.snapshot.element[10].mapping[1].identity","column":["a31"]},{"path":"StructureDefinition.snapshot.element[10].mapping[1].map","column":["a32"]},{"path":"StructureDefinition.snapshot.element[10].mapping[2].identity","column":["a33"]},{"path":"StructureDefinition.snapshot.element[10].mapping[2].map","column":["a34"]},{"path":"StructureDefinition.snapshot.element[11].id","column":["a35"]},{"path":"StructureDefinition.snapshot.element[11].path","column":["a36"]},{"path":"StructureDefinition.snapshot.element[11].short","column":["a37"]},{"path":"StructureDefinition.snapshot.element[11].definition","column":["a38"]},{"path":"StructureDefinition.snapshot.element[11].comment","column":["a39"]},{"path":"StructureDefinition.snapshot.element[11].min","column":["a40"]},{"path":"StructureDefinition.snapshot.element[11].max","column":["a41"]},{"path":"StructureDefinition.snapshot.element[11].base.path","column":["a42"]},{"path":"StructureDefinition.snapshot.element[11].base.min","column":["a43"]},{"path":"StructureDefinition.snapshot.element[11].base.max","column":["a44"]},{"path":"StructureDefinition.snapshot.element[11].type[0].code","column":["a45"]},{"path":"StructureDefinition.snapshot.element[11].constraint[0].key","column":["a46"]},{"path":"StructureDefinition.snapshot.element[11].constraint[0].severity","column":["a47"]},{"path":"StructureDefinition.snapshot.element[11].constraint[0].human","column":["a48"]},{"path":"StructureDefinition.snapshot.element[11].constraint[0].expression","column":["a49"]},{"path":"StructureDefinition.snapshot.element[11].constraint[0].xpath","column":["a50"]},{"path":"StructureDefinition.snapshot.element[11].constraint[0].source","column":["a51"]},{"path":"StructureDefinition.snapshot.element[11].isModifier","column":["a52"]},{"path":"StructureDefinition.snapshot.element[11].isModifierReason","column":["a53"]},{"path":"StructureDefinition.snapshot.element[11].isSummary","column":["a54"]},{"path":"StructureDefinition.snapshot.element[11].binding.extension[0].url","column":["a55"]},{"path":"StructureDefinition.snapshot.element[11].binding.extension[0].valueString","column":["a56"]},{"path":"StructureDefinition.snapshot.element[11].binding.strength","column":["a57"]},{"path":"StructureDefinition.snapshot.element[11].binding.description","column":["a58"]},{"path":"StructureDefinition.snapshot.element[11].binding.valueSet","column":["a59"]},{"path":"StructureDefinition.snapshot.element[11].mapping[0].identity","column":["a60"]},{"path":"StructureDefinition.snapshot.element[11].mapping[0].map","column":["a61"]},{"path":"StructureDefinition.snapshot.element[11].mapping[1].identity","column":["a62"]},{"path":"StructureDefinition.snapshot.element[11].mapping[1].map","column":["a63"]},{"path":"StructureDefinition.snapshot.element[11].mapping[2].identity","column":["a64"]},{"path":"StructureDefinition.snapshot.element[11].mapping[2].map","column":["a65"]},{"path":"StructureDefinition.snapshot.element[11].mapping[3].identity","column":["a66"]},{"path":"StructureDefinition.snapshot.element[11].mapping[3].map","column":["a67"]},{"path":"StructureDefinition.snapshot.element[12].id","column":["a68"]},{"path":"StructureDefinition.snapshot.element[12].path","column":["a69"]},{"path":"StructureDefinition.snapshot.element[12].short","column":["a70"]},{"path":"StructureDefinition.snapshot.element[12].definition","column":["a71"]},{"path":"StructureDefinition.snapshot.element[12].min","column":["a72"]},{"path":"StructureDefinition.snapshot.element[12].max","column":["a73"]},{"path":"StructureDefinition.snapshot.element[12].base.path","column":["a74"]},{"path":"StructureDefinition.snapshot.element[12].base.min","column":["a75"]},{"path":"StructureDefinition.snapshot.element[12].base.max","column":["a76"]},{"path":"StructureDefinition.snapshot.element[12].type[0].code","column":["a77"]},{"path":"StructureDefinition.snapshot.element[12].type[0].targetProfile[0]","column":["a78"]},{"path":"StructureDefinition.snapshot.element[12].type[0].targetProfile[1]","column":["a79"]},{"path":"StructureDefinition.snapshot.element[12].constraint[0].key","column":["a80"]},{"path":"StructureDefinition.snapshot.element[12].constraint[0].severity","column":["a81"]},{"path":"StructureDefinition.snapshot.element[12].constraint[0].human","column":["a82"]},{"path":"StructureDefinition.snapshot.element[12].constraint[0].expression","column":["a83"]},{"path":"StructureDefinition.snapshot.element[12].constraint[0].xpath","column":["a84"]},{"path":"StructureDefinition.snapshot.element[12].constraint[0].source","column":["a85"]},{"path":"StructureDefinition.snapshot.element[12].isModifier","column":["a86"]},{"path":"StructureDefinition.snapshot.element[12].isSummary","column":["a87"]},{"path":"StructureDefinition.snapshot.element[12].mapping[0].identity","column":["a88"]},{"path":"StructureDefinition.snapshot.element[12].mapping[0].map","column":["a89"]},{"path":"StructureDefinition.snapshot.element[12].mapping[1].identity","column":["a90"]},{"path":"StructureDefinition.snapshot.element[12].mapping[1].map","column":["a91"]},{"path":"StructureDefinition.snapshot.element[12].mapping[2].identity","column":["a92"]},{"path":"StructureDefinition.snapshot.element[12].mapping[2].map","column":["a93"]},{"path":"StructureDefinition.snapshot.element[12].mapping[3].identity","column":["a94"]},{"path":"StructureDefinition.snapshot.element[12].mapping[3].map","column":["a95"]},{"path":"StructureDefinition.snapshot.element[13].id","column":["a96"]},{"path":"StructureDefinition.snapshot.element[13].path","column":["a97"]},{"path":"StructureDefinition.snapshot.element[13].short","column":["a98"]},{"path":"StructureDefinition.snapshot.element[13].definition","column":["a99"]},{"path":"StructureDefinition.snapshot.element[13].comment","column":["a100"]},{"path":"StructureDefinition.snapshot.element[13].min","column":["a101"]},{"path":"StructureDefinition.snapshot.element[13].max","column":["a102"]},{"path":"StructureDefinition.snapshot.element[13].base.path","column":["a103"]},{"path":"StructureDefinition.snapshot.element[13].base.min","column":["a104"]},{"path":"StructureDefinition.snapshot.element[13].base.max","column":["a105"]},{"path":"StructureDefinition.snapshot.element[13].type[0].code","column":["a106"]},{"path":"StructureDefinition.snapshot.element[13].type[0].targetProfile[0]","column":["a107"]},{"path":"StructureDefinition.snapshot.element[13].type[0].targetProfile[1]","column":["a108"]},{"path":"StructureDefinition.snapshot.element[13].type[0].targetProfile[2]","column":["a109"]},{"path":"StructureDefinition.snapshot.element[13].type[0].targetProfile[3]","column":["a110"]},{"path":"StructureDefinition.snapshot.element[13].type[0].targetProfile[4]","column":["a111"]},{"path":"StructureDefinition.snapshot.element[13].type[0].targetProfile[5]","column":["a112"]},{"path":"StructureDefinition.snapshot.element[13].constraint[0].key","column":["a113"]},{"path":"StructureDefinition.snapshot.element[13].constraint[0].severity","column":["a114"]},{"path":"StructureDefinition.snapshot.element[13].constraint[0].human","column":["a115"]},{"path":"StructureDefinition.snapshot.element[13].constraint[0].expression","column":["a116"]},{"path":"StructureDefinition.snapshot.element[13].constraint[0].xpath","column":["a117"]},{"path":"StructureDefinition.snapshot.element[13].constraint[0].source","column":["a118"]},{"path":"StructureDefinition.snapshot.element[13].isModifier","column":["a119"]},{"path":"StructureDefinition.snapshot.element[13].isSummary","column":["a120"]},{"path":"StructureDefinition.snapshot.element[14].id","column":["a121"]},{"path":"StructureDefinition.snapshot.element[14].path","column":["a122"]},{"path":"StructureDefinition.snapshot.element[14].short","column":["a123"]},{"path":"StructureDefinition.snapshot.element[14].definition","column":["a124"]},{"path":"StructureDefinition.snapshot.element[14].min","column":["a125"]},{"path":"StructureDefinition.snapshot.element[14].max","column":["a126"]},{"path":"StructureDefinition.snapshot.element[14].base.path","column":["a127"]},{"path":"StructureDefinition.snapshot.element[14].base.min","column":["a128"]},{"path":"StructureDefinition.snapshot.element[14].base.max","column":["a129"]},{"path":"StructureDefinition.snapshot.element[14].type[0].code","column":["a130"]},{"path":"StructureDefinition.snapshot.element[14].type[1].code","column":["a131"]},{"path":"StructureDefinition.snapshot.element[14].type[2].code","column":["a132"]},{"path":"StructureDefinition.snapshot.element[14].constraint[0].key","column":["a133"]},{"path":"StructureDefinition.snapshot.element[14].constraint[0].severity","column":["a134"]},{"path":"StructureDefinition.snapshot.element[14].constraint[0].human","column":["a135"]},{"path":"StructureDefinition.snapshot.element[14].constraint[0].expression","column":["a136"]},{"path":"StructureDefinition.snapshot.element[14].constraint[0].xpath","column":["a137"]},{"path":"StructureDefinition.snapshot.element[14].constraint[0].source","column":["a138"]},{"path":"StructureDefinition.snapshot.element[14].isModifier","column":["a139"]},{"path":"StructureDefinition.snapshot.element[14].isSummary","column":["a140"]},{"path":"StructureDefinition.snapshot.element[14].mapping[0].identity","column":["a141"]},{"path":"StructureDefinition.snapshot.element[14].mapping[0].map","column":["a142"]},{"path":"StructureDefinition.snapshot.element[14].mapping[1].identity","column":["a143"]},{"path":"StructureDefinition.snapshot.element[14].mapping[1].map","column":["a144"]},{"path":"StructureDefinition.snapshot.element[14].mapping[2].identity","column":["a145"]},{"path":"StructureDefinition.snapshot.element[14].mapping[2].map","column":["a146"]},{"path":"StructureDefinition.snapshot.element[15].id","column":["a147"]},{"path":"StructureDefinition.snapshot.element[15].path","column":["a148"]},{"path":"StructureDefinition.snapshot.element[15].short","column":["a149"]}]},{"class":"StructureDefinition","view":{"tableName":"a145713959_3"},"identifier":[{"path":"StructureDefinition","column":["_subject"]}],"mapping":[{"path":"StructureDefinition.snapshot.element[15].definition","column":["a1"]},{"path":"StructureDefinition.snapshot.element[15].min","column":["a2"]},{"path":"StructureDefinition.snapshot.element[15].max","column":["a3"]},{"path":"StructureDefinition.snapshot.element[15].base.path","column":["a4"]},{"path":"StructureDefinition.snapshot.element[15].base.min","column":["a5"]},{"path":"StructureDefinition.snapshot.element[15].base.max","column":["a6"]},{"path":"StructureDefinition.snapshot.element[15].type[0].code","column":["a7"]},{"path":"StructureDefinition.snapshot.element[15].constraint[0].key","column":["a8"]},{"path":"StructureDefinition.snapshot.element[15].constraint[0].severity","column":["a9"]},{"path":"StructureDefinition.snapshot.element[15].constraint[0].human","column":["a10"]},{"path":"StructureDefinition.snapshot.element[15].constraint[0].expression","column":["a11"]},{"path":"StructureDefinition.snapshot.element[15].constraint[0].xpath","column":["a12"]},{"path":"StructureDefinition.snapshot.element[15].constraint[0].source","column":["a13"]},{"path":"StructureDefinition.snapshot.element[15].isModifier","column":["a14"]},{"path":"StructureDefinition.snapshot.element[15].isSummary","column":["a15"]},{"path":"StructureDefinition.snapshot.element[15].mapping[0].identity","column":["a16"]},{"path":"StructureDefinition.snapshot.element[15].mapping[0].map","column":["a17"]},{"path":"StructureDefinition.snapshot.element[15].mapping[1].identity","column":["a18"]},{"path":"StructureDefinition.snapshot.element[15].mapping[1].map","column":["a19"]},{"path":"StructureDefinition.snapshot.element[16].id","column":["a20"]},{"path":"StructureDefinition.snapshot.element[16].path","column":["a21"]},{"path":"StructureDefinition.snapshot.element[16].short","column":["a22"]},{"path":"StructureDefinition.snapshot.element[16].definition","column":["a23"]},{"path":"StructureDefinition.snapshot.element[16].min","column":["a24"]},{"path":"StructureDefinition.snapshot.element[16].max","column":["a25"]},{"path":"StructureDefinition.snapshot.element[16].base.path","column":["a26"]},{"path":"StructureDefinition.snapshot.element[16].base.min","column":["a27"]},{"path":"StructureDefinition.snapshot.element[16].base.max","column":["a28"]},{"path":"StructureDefinition.snapshot.element[16].type[0].code","column":["a29"]},{"path":"StructureDefinition.snapshot.element[16].type[0].targetProfile[0]","column":["a30"]},{"path":"StructureDefinition.snapshot.element[16].type[0].targetProfile[1]","column":["a31"]},{"path":"StructureDefinition.snapshot.element[16].type[0].targetProfile[2]","column":["a32"]},{"path":"StructureDefinition.snapshot.element[16].type[0].targetProfile[3]","column":["a33"]},{"path":"StructureDefinition.snapshot.element[16].constraint[0].key","column":["a34"]},{"path":"StructureDefinition.snapshot.element[16].constraint[0].severity","column":["a35"]},{"path":"StructureDefinition.snapshot.element[16].constraint[0].human","column":["a36"]},{"path":"StructureDefinition.snapshot.element[16].constraint[0].expression","column":["a37"]},{"path":"StructureDefinition.snapshot.element[16].constraint[0].xpath","column":["a38"]},{"path":"StructureDefinition.snapshot.element[16].constraint[0].source","column":["a39"]},{"path":"StructureDefinition.snapshot.element[16].isModifier","column":["a40"]},{"path":"StructureDefinition.snapshot.element[16].isSummary","column":["a41"]},{"path":"StructureDefinition.snapshot.element[16].mapping[0].identity","column":["a42"]},{"path":"StructureDefinition.snapshot.element[16].mapping[0].map","column":["a43"]},{"path":"StructureDefinition.snapshot.element[16].mapping[1].identity","column":["a44"]},{"path":"StructureDefinition.snapshot.element[16].mapping[1].map","column":["a45"]},{"path":"StructureDefinition.snapshot.element[17].id","column":["a46"]},{"path":"StructureDefinition.snapshot.element[17].path","column":["a47"]},{"path":"StructureDefinition.snapshot.element[17].short","column":["a48"]},{"path":"StructureDefinition.snapshot.element[17].definition","column":["a49"]},{"path":"StructureDefinition.snapshot.element[17].min","column":["a50"]},{"path":"StructureDefinition.snapshot.element[17].max","column":["a51"]},{"path":"StructureDefinition.snapshot.element[17].base.path","column":["a52"]},{"path":"StructureDefinition.snapshot.element[17].base.min","column":["a53"]},{"path":"StructureDefinition.snapshot.element[17].base.max","column":["a54"]},{"path":"StructureDefinition.snapshot.element[17].type[0].code","column":["a55"]},{"path":"StructureDefinition.snapshot.element[17].type[0].targetProfile[0]","column":["a56"]},{"path":"StructureDefinition.snapshot.element[17].constraint[0].key","column":["a57"]},{"path":"StructureDefinition.snapshot.element[17].constraint[0].severity","column":["a58"]},{"path":"StructureDefinition.snapshot.element[17].constraint[0].human","column":["a59"]},{"path":"StructureDefinition.snapshot.element[17].constraint[0].expression","column":["a60"]},{"path":"StructureDefinition.snapshot.element[17].constraint[0].xpath","column":["a61"]},{"path":"StructureDefinition.snapshot.element[17].constraint[0].source","column":["a62"]},{"path":"StructureDefinition.snapshot.element[17].isModifier","column":["a63"]},{"path":"StructureDefinition.snapshot.element[17].isSummary","column":["a64"]},{"path":"StructureDefinition.snapshot.element[17].mapping[0].identity","column":["a65"]},{"path":"StructureDefinition.snapshot.element[17].mapping[0].map","column":["a66"]},{"path":"StructureDefinition.snapshot.element[17].mapping[1].identity","column":["a67"]},{"path":"StructureDefinition.snapshot.element[17].mapping[1].map","column":["a68"]},{"path":"StructureDefinition.snapshot.element[18].id","column":["a69"]},{"path":"StructureDefinition.snapshot.element[18].path","column":["a70"]},{"path":"StructureDefinition.snapshot.element[18].short","column":["a71"]},{"path":"StructureDefinition.snapshot.element[18].definition","column":["a72"]},{"path":"StructureDefinition.snapshot.element[18].min","column":["a73"]},{"path":"StructureDefinition.snapshot.element[18].max","column":["a74"]},{"path":"StructureDefinition.snapshot.element[18].base.path","column":["a75"]},{"path":"StructureDefinition.snapshot.element[18].base.min","column":["a76"]},{"path":"StructureDefinition.snapshot.element[18].base.max","column":["a77"]},{"path":"StructureDefinition.snapshot.element[18].type[0].code","column":["a78"]},{"path":"StructureDefinition.snapshot.element[18].constraint[0].key","column":["a79"]},{"path":"StructureDefinition.snapshot.element[18].constraint[0].severity","column":["a80"]},{"path":"StructureDefinition.snapshot.element[18].constraint[0].human","column":["a81"]},{"path":"StructureDefinition.snapshot.element[18].constraint[0].expression","column":["a82"]},{"path":"StructureDefinition.snapshot.element[18].constraint[0].xpath","column":["a83"]},{"path":"StructureDefinition.snapshot.element[18].constraint[0].source","column":["a84"]},{"path":"StructureDefinition.snapshot.element[18].isModifier","column":["a85"]},{"path":"StructureDefinition.snapshot.element[18].isSummary","column":["a86"]},{"path":"StructureDefinition.snapshot.element[18].mapping[0].identity","column":["a87"]},{"path":"StructureDefinition.snapshot.element[18].mapping[0].map","column":["a88"]},{"path":"StructureDefinition.snapshot.element[18].mapping[1].identity","column":["a89"]},{"path":"StructureDefinition.snapshot.element[18].mapping[1].map","column":["a90"]},{"path":"StructureDefinition.snapshot.element[18].mapping[2].identity","column":["a91"]},{"path":"StructureDefinition.snapshot.element[18].mapping[2].map","column":["a92"]},{"path":"StructureDefinition.snapshot.element[19].id","column":["a93"]},{"path":"StructureDefinition.snapshot.element[19].path","column":["a94"]},{"path":"StructureDefinition.snapshot.element[19].short","column":["a95"]},{"path":"StructureDefinition.snapshot.element[19].definition","column":["a96"]},{"path":"StructureDefinition.snapshot.element[19].min","column":["a97"]},{"path":"StructureDefinition.snapshot.element[19].max","column":["a98"]},{"path":"StructureDefinition.snapshot.element[19].base.path","column":["a99"]},{"path":"StructureDefinition.snapshot.element[19].base.min","column":["a100"]},{"path":"StructureDefinition.snapshot.element[19].base.max","column":["a101"]},{"path":"StructureDefinition.snapshot.element[19].type[0].code","column":["a102"]},{"path":"StructureDefinition.snapshot.element[19].type[0].targetProfile[0]","column":["a103"]},{"path":"StructureDefinition.snapshot.element[19].type[0].targetProfile[1]","column":["a104"]},{"path":"StructureDefinition.snapshot.element[19].type[0].targetProfile[2]","column":["a105"]},{"path":"StructureDefinition.snapshot.element[19].type[0].targetProfile[3]","column":["a106"]},{"path":"StructureDefinition.snapshot.element[19].type[0].targetProfile[4]","column":["a107"]},{"path":"StructureDefinition.snapshot.element[19].constraint[0].key","column":["a108"]},{"path":"StructureDefinition.snapshot.element[19].constraint[0].severity","column":["a109"]},{"path":"StructureDefinition.snapshot.element[19].constraint[0].human","column":["a110"]},{"path":"StructureDefinition.snapshot.element[19].constraint[0].expression","column":["a111"]},{"path":"StructureDefinition.snapshot.element[19].constraint[0].xpath","column":["a112"]},{"path":"StructureDefinition.snapshot.element[19].constraint[0].source","column":["a113"]},{"path":"StructureDefinition.snapshot.element[19].isModifier","column":["a114"]},{"path":"StructureDefinition.snapshot.element[19].isSummary","column":["a115"]},{"path":"StructureDefinition.snapshot.element[19].mapping[0].identity","column":["a116"]},{"path":"StructureDefinition.snapshot.element[19].mapping[0].map","column":["a117"]},{"path":"StructureDefinition.snapshot.element[19].mapping[1].identity","column":["a118"]},{"path":"StructureDefinition.snapshot.element[19].mapping[1].map","column":["a119"]},{"path":"StructureDefinition.snapshot.element[19].mapping[2].identity","column":["a120"]},{"path":"StructureDefinition.snapshot.element[19].mapping[2].map","column":["a121"]},{"path":"StructureDefinition.snapshot.element[19].mapping[3].identity","column":["a122"]},{"path":"StructureDefinition.snapshot.element[19].mapping[3].map","column":["a123"]},{"path":"StructureDefinition.snapshot.element[20].id","column":["a124"]},{"path":"StructureDefinition.snapshot.element[20].path","column":["a125"]},{"path":"StructureDefinition.snapshot.element[20].short","column":["a126"]},{"path":"StructureDefinition.snapshot.element[20].definition","column":["a127"]},{"path":"StructureDefinition.snapshot.element[20].requirements","column":["a128"]},{"path":"StructureDefinition.snapshot.element[20].min","column":["a129"]},{"path":"StructureDefinition.snapshot.element[20].max","column":["a130"]},{"path":"StructureDefinition.snapshot.element[20].base.path","column":["a131"]},{"path":"StructureDefinition.snapshot.element[20].base.min","column":["a132"]},{"path":"StructureDefinition.snapshot.element[20].base.max","column":["a133"]},{"path":"StructureDefinition.snapshot.element[20].type[0].code","column":["a134"]},{"path":"StructureDefinition.snapshot.element[20].constraint[0].key","column":["a135"]},{"path":"StructureDefinition.snapshot.element[20].constraint[0].severity","column":["a136"]},{"path":"StructureDefinition.snapshot.element[20].constraint[0].human","column":["a137"]},{"path":"StructureDefinition.snapshot.element[20].constraint[0].expression","column":["a138"]},{"path":"StructureDefinition.snapshot.element[20].constraint[0].xpath","column":["a139"]},{"path":"StructureDefinition.snapshot.element[20].constraint[0].source","column":["a140"]},{"path":"StructureDefinition.snapshot.element[20].isModifier","column":["a141"]},{"path":"StructureDefinition.snapshot.element[20].isSummary","column":["a142"]},{"path":"StructureDefinition.snapshot.element[20].binding.extension[0].url","column":["a143"]},{"path":"StructureDefinition.snapshot.element[20].binding.extension[0].valueString","column":["a144"]},{"path":"StructureDefinition.snapshot.element[20].binding.strength","column":["a145"]},{"path":"StructureDefinition.snapshot.element[20].binding.description","column":["a146"]},{"path":"StructureDefinition.snapshot.element[20].binding.valueSet","column":["a147"]},{"path":"StructureDefinition.snapshot.element[20].mapping[0].identity","column":["a148"]},{"path":"StructureDefinition.snapshot.element[20].mapping[0].map","column":["a149"]}]},{"class":"StructureDefinition","view":{"tableName":"a145713959_4"},"identifier":[{"path":"StructureDefinition","column":["_subject"]}],"mapping":[{"path":"StructureDefinition.snapshot.element[20].mapping[1].identity","column":["a1"]},{"path":"StructureDefinition.snapshot.element[20].mapping[1].map","column":["a2"]},{"path":"StructureDefinition.snapshot.element[21].id","column":["a3"]},{"path":"StructureDefinition.snapshot.element[21].path","column":["a4"]},{"path":"StructureDefinition.snapshot.element[21].short","column":["a5"]},{"path":"StructureDefinition.snapshot.element[21].definition","column":["a6"]},{"path":"StructureDefinition.snapshot.element[21].min","column":["a7"]},{"path":"StructureDefinition.snapshot.element[21].max","column":["a8"]},{"path":"StructureDefinition.snapshot.element[21].base.path","column":["a9"]},{"path":"StructureDefinition.snapshot.element[21].base.min","column":["a10"]},{"path":"StructureDefinition.snapshot.element[21].base.max","column":["a11"]},{"path":"StructureDefinition.snapshot.element[21].type[0].code","column":["a12"]},{"path":"StructureDefinition.snapshot.element[21].constraint[0].key","column":["a13"]},{"path":"StructureDefinition.snapshot.element[21].constraint[0].severity","column":["a14"]},{"path":"StructureDefinition.snapshot.element[21].constraint[0].human","column":["a15"]},{"path":"StructureDefinition.snapshot.element[21].constraint[0].expression","column":["a16"]},{"path":"StructureDefinition.snapshot.element[21].constraint[0].xpath","column":["a17"]},{"path":"StructureDefinition.snapshot.element[21].constraint[0].source","column":["a18"]},{"path":"StructureDefinition.snapshot.element[21].isModifier","column":["a19"]},{"path":"StructureDefinition.snapshot.element[21].isSummary","column":["a20"]},{"path":"StructureDefinition.snapshot.element[21].mapping[0].identity","column":["a21"]},{"path":"StructureDefinition.snapshot.element[21].mapping[0].map","column":["a22"]},{"path":"StructureDefinition.snapshot.element[21].mapping[1].identity","column":["a23"]},{"path":"StructureDefinition.snapshot.element[21].mapping[1].map","column":["a24"]},{"path":"StructureDefinition.differential.element[0].id","column":["a25"]},{"path":"StructureDefinition.differential.element[0].path","column":["a26"]},{"path":"StructureDefinition.differential.element[0].short","column":["a27"]},{"path":"StructureDefinition.differential.element[0].definition","column":["a28"]},{"path":"StructureDefinition.differential.element[0].min","column":["a29"]},{"path":"StructureDefinition.differential.element[0].max","column":["a30"]},{"path":"StructureDefinition.differential.element[0].mapping[0].identity","column":["a31"]},{"path":"StructureDefinition.differential.element[0].mapping[0].map","column":["a32"]},{"path":"StructureDefinition.differential.element[0].mapping[1].identity","column":["a33"]},{"path":"StructureDefinition.differential.element[0].mapping[1].map","column":["a34"]},{"path":"StructureDefinition.differential.element[1].id","column":["a35"]},{"path":"StructureDefinition.differential.element[1].path","column":["a36"]},{"path":"StructureDefinition.differential.element[1].short","column":["a37"]},{"path":"StructureDefinition.differential.element[1].definition","column":["a38"]},{"path":"StructureDefinition.differential.element[1].min","column":["a39"]},{"path":"StructureDefinition.differential.element[1].max","column":["a40"]},{"path":"StructureDefinition.differential.element[1].type[0].code","column":["a41"]},{"path":"StructureDefinition.differential.element[1].isSummary","column":["a42"]},{"path":"StructureDefinition.differential.element[1].mapping[0].identity","column":["a43"]},{"path":"StructureDefinition.differential.element[1].mapping[0].map","column":["a44"]},{"path":"StructureDefinition.differential.element[1].mapping[1].identity","column":["a45"]},{"path":"StructureDefinition.differential.element[1].mapping[1].map","column":["a46"]},{"path":"StructureDefinition.differential.element[1].mapping[2].identity","column":["a47"]},{"path":"StructureDefinition.differential.element[1].mapping[2].map","column":["a48"]},{"path":"StructureDefinition.differential.element[2].id","column":["a49"]},{"path":"StructureDefinition.differential.element[2].path","column":["a50"]},{"path":"StructureDefinition.differential.element[2].short","column":["a51"]},{"path":"StructureDefinition.differential.element[2].definition","column":["a52"]},{"path":"StructureDefinition.differential.element[2].requirements","column":["a53"]},{"path":"StructureDefinition.differential.element[2].alias[0]","column":["a54"]},{"path":"StructureDefinition.differential.element[2].min","column":["a55"]},{"path":"StructureDefinition.differential.element[2].max","column":["a56"]},{"path":"StructureDefinition.differential.element[2].type[0].code","column":["a57"]},{"path":"StructureDefinition.differential.element[2].type[0].targetProfile[0]","column":["a58"]},{"path":"StructureDefinition.differential.element[2].isSummary","column":["a59"]},{"path":"StructureDefinition.differential.element[2].mapping[0].identity","column":["a60"]},{"path":"StructureDefinition.differential.element[2].mapping[0].map","column":["a61"]},{"path":"StructureDefinition.differential.element[2].mapping[1].identity","column":["a62"]},{"path":"StructureDefinition.differential.element[2].mapping[1].map","column":["a63"]},{"path":"StructureDefinition.differential.element[2].mapping[2].identity","column":["a64"]},{"path":"StructureDefinition.differential.element[2].mapping[2].map","column":["a65"]},{"path":"StructureDefinition.differential.element[3].id","column":["a66"]},{"path":"StructureDefinition.differential.element[3].path","column":["a67"]},{"path":"StructureDefinition.differential.element[3].short","column":["a68"]},{"path":"StructureDefinition.differential.element[3].definition","column":["a69"]},{"path":"StructureDefinition.differential.element[3].comment","column":["a70"]},{"path":"StructureDefinition.differential.element[3].min","column":["a71"]},{"path":"StructureDefinition.differential.element[3].max","column":["a72"]},{"path":"StructureDefinition.differential.element[3].type[0].code","column":["a73"]},{"path":"StructureDefinition.differential.element[3].isModifier","column":["a74"]},{"path":"StructureDefinition.differential.element[3].isModifierReason","column":["a75"]},{"path":"StructureDefinition.differential.element[3].isSummary","column":["a76"]},{"path":"StructureDefinition.differential.element[3].binding.extension[0].url","column":["a77"]},{"path":"StructureDefinition.differential.element[3].binding.extension[0].valueString","column":["a78"]},{"path":"StructureDefinition.differential.element[3].binding.strength","column":["a79"]},{"path":"StructureDefinition.differential.element[3].binding.description","column":["a80"]},{"path":"StructureDefinition.differential.element[3].binding.valueSet","column":["a81"]},{"path":"StructureDefinition.differential.element[3].mapping[0].identity","column":["a82"]},{"path":"StructureDefinition.differential.element[3].mapping[0].map","column":["a83"]},{"path":"StructureDefinition.differential.element[3].mapping[1].identity","column":["a84"]},{"path":"StructureDefinition.differential.element[3].mapping[1].map","column":["a85"]},{"path":"StructureDefinition.differential.element[3].mapping[2].identity","column":["a86"]},{"path":"StructureDefinition.differential.element[3].mapping[2].map","column":["a87"]},{"path":"StructureDefinition.differential.element[3].mapping[3].identity","column":["a88"]},{"path":"StructureDefinition.differential.element[3].mapping[3].map","column":["a89"]},{"path":"StructureDefinition.differential.element[4].id","column":["a90"]},{"path":"StructureDefinition.differential.element[4].path","column":["a91"]},{"path":"StructureDefinition.differential.element[4].short","column":["a92"]},{"path":"StructureDefinition.differential.element[4].definition","column":["a93"]},{"path":"StructureDefinition.differential.element[4].min","column":["a94"]},{"path":"StructureDefinition.differential.element[4].max","column":["a95"]},{"path":"StructureDefinition.differential.element[4].type[0].code","column":["a96"]},{"path":"StructureDefinition.differential.element[4].type[0].targetProfile[0]","column":["a97"]},{"path":"StructureDefinition.differential.element[4].type[0].targetProfile[1]","column":["a98"]},{"path":"StructureDefinition.differential.element[4].isSummary","column":["a99"]},{"path":"StructureDefinition.differential.element[4].mapping[0].identity","column":["a100"]},{"path":"StructureDefinition.differential.element[4].mapping[0].map","column":["a101"]},{"path":"StructureDefinition.differential.element[4].mapping[1].identity","column":["a102"]},{"path":"StructureDefinition.differential.element[4].mapping[1].map","column":["a103"]},{"path":"StructureDefinition.differential.element[4].mapping[2].identity","column":["a104"]},{"path":"StructureDefinition.differential.element[4].mapping[2].map","column":["a105"]},{"path":"StructureDefinition.differential.element[4].mapping[3].identity","column":["a106"]},{"path":"StructureDefinition.differential.element[4].mapping[3].map","column":["a107"]},{"path":"StructureDefinition.differential.element[5].id","column":["a108"]},{"path":"StructureDefinition.differential.element[5].path","column":["a109"]},{"path":"StructureDefinition.differential.element[5].short","column":["a110"]},{"path":"StructureDefinition.differential.element[5].definition","column":["a111"]},{"path":"StructureDefinition.differential.element[5].comment","column":["a112"]},{"path":"StructureDefinition.differential.element[5].min","column":["a113"]},{"path":"StructureDefinition.differential.element[5].max","column":["a114"]},{"path":"StructureDefinition.differential.element[5].type[0].code","column":["a115"]},{"path":"StructureDefinition.differential.element[5].type[0].targetProfile[0]","column":["a116"]},{"path":"StructureDefinition.differential.element[5].type[0].targetProfile[1]","column":["a117"]},{"path":"StructureDefinition.differential.element[5].type[0].targetProfile[2]","column":["a118"]},{"path":"StructureDefinition.differential.element[5].type[0].targetProfile[3]","column":["a119"]},{"path":"StructureDefinition.differential.element[5].type[0].targetProfile[4]","column":["a120"]},{"path":"StructureDefinition.differential.element[5].type[0].targetProfile[5]","column":["a121"]},{"path":"StructureDefinition.differential.element[5].isSummary","column":["a122"]},{"path":"StructureDefinition.differential.element[6].id","column":["a123"]},{"path":"StructureDefinition.differential.element[6].path","column":["a124"]},{"path":"StructureDefinition.differential.element[6].short","column":["a125"]},{"path":"StructureDefinition.differential.element[6].definition","column":["a126"]},{"path":"StructureDefinition.differential.element[6].min","column":["a127"]},{"path":"StructureDefinition.differential.element[6].max","column":["a128"]},{"path":"StructureDefinition.differential.element[6].type[0].code","column":["a129"]},{"path":"StructureDefinition.differential.element[6].type[1].code","column":["a130"]},{"path":"StructureDefinition.differential.element[6].type[2].code","column":["a131"]},{"path":"StructureDefinition.differential.element[6].isSummary","column":["a132"]},{"path":"StructureDefinition.differential.element[6].mapping[0].identity","column":["a133"]},{"path":"StructureDefinition.differential.element[6].mapping[0].map","column":["a134"]},{"path":"StructureDefinition.differential.element[6].mapping[1].identity","column":["a135"]},{"path":"StructureDefinition.differential.element[6].mapping[1].map","column":["a136"]},{"path":"StructureDefinition.differential.element[6].mapping[2].identity","column":["a137"]},{"path":"StructureDefinition.differential.element[6].mapping[2].map","column":["a138"]},{"path":"StructureDefinition.differential.element[7].id","column":["a139"]},{"path":"StructureDefinition.differential.element[7].path","column":["a140"]},{"path":"StructureDefinition.differential.element[7].short","column":["a141"]},{"path":"StructureDefinition.differential.element[7].definition","column":["a142"]},{"path":"StructureDefinition.differential.element[7].min","column":["a143"]},{"path":"StructureDefinition.differential.element[7].max","column":["a144"]},{"path":"StructureDefinition.differential.element[7].type[0].code","column":["a145"]},{"path":"StructureDefinition.differential.element[7].isSummary","column":["a146"]},{"path":"StructureDefinition.differential.element[7].mapping[0].identity","column":["a147"]},{"path":"StructureDefinition.differential.element[7].mapping[0].map","column":["a148"]},{"path":"StructureDefinition.differential.element[7].mapping[1].identity","column":["a149"]}]},{"class":"StructureDefinition","view":{"tableName":"a145713959_5"},"identifier":[{"path":"StructureDefinition","column":["_subject"]}],"mapping":[{"path":"StructureDefinition.differential.element[7].mapping[1].map","column":["a1"]},{"path":"StructureDefinition.differential.element[8].id","column":["a2"]},{"path":"StructureDefinition.differential.element[8].path","column":["a3"]},{"path":"StructureDefinition.differential.element[8].short","column":["a4"]},{"path":"StructureDefinition.differential.element[8].definition","column":["a5"]},{"path":"StructureDefinition.differential.element[8].min","column":["a6"]},{"path":"StructureDefinition.differential.element[8].max","column":["a7"]},{"path":"StructureDefinition.differential.element[8].type[0].code","column":["a8"]},{"path":"StructureDefinition.differential.element[8].type[0].targetProfile[0]","column":["a9"]},{"path":"StructureDefinition.differential.element[8].type[0].targetProfile[1]","column":["a10"]},{"path":"StructureDefinition.differential.element[8].type[0].targetProfile[2]","column":["a11"]},{"path":"StructureDefinition.differential.element[8].type[0].targetProfile[3]","column":["a12"]},{"path":"StructureDefinition.differential.element[8].isSummary","column":["a13"]},{"path":"StructureDefinition.differential.element[8].mapping[0].identity","column":["a14"]},{"path":"StructureDefinition.differential.element[8].mapping[0].map","column":["a15"]},{"path":"StructureDefinition.differential.element[8].mapping[1].identity","column":["a16"]},{"path":"StructureDefinition.differential.element[8].mapping[1].map","column":["a17"]},{"path":"StructureDefinition.differential.element[9].id","column":["a18"]},{"path":"StructureDefinition.differential.element[9].path","column":["a19"]},{"path":"StructureDefinition.differential.element[9].short","column":["a20"]},{"path":"StructureDefinition.differential.element[9].definition","column":["a21"]},{"path":"StructureDefinition.differential.element[9].min","column":["a22"]},{"path":"StructureDefinition.differential.element[9].max","column":["a23"]},{"path":"StructureDefinition.differential.element[9].type[0].code","column":["a24"]},{"path":"StructureDefinition.differential.element[9].type[0].targetProfile[0]","column":["a25"]},{"path":"StructureDefinition.differential.element[9].isSummary","column":["a26"]},{"path":"StructureDefinition.differential.element[9].mapping[0].identity","column":["a27"]},{"path":"StructureDefinition.differential.element[9].mapping[0].map","column":["a28"]},{"path":"StructureDefinition.differential.element[9].mapping[1].identity","column":["a29"]},{"path":"StructureDefinition.differential.element[9].mapping[1].map","column":["a30"]},{"path":"StructureDefinition.differential.element[10].id","column":["a31"]},{"path":"StructureDefinition.differential.element[10].path","column":["a32"]},{"path":"StructureDefinition.differential.element[10].short","column":["a33"]},{"path":"StructureDefinition.differential.element[10].definition","column":["a34"]},{"path":"StructureDefinition.differential.element[10].min","column":["a35"]},{"path":"StructureDefinition.differential.element[10].max","column":["a36"]},{"path":"StructureDefinition.differential.element[10].type[0].code","column":["a37"]},{"path":"StructureDefinition.differential.element[10].isSummary","column":["a38"]},{"path":"StructureDefinition.differential.element[10].mapping[0].identity","column":["a39"]},{"path":"StructureDefinition.differential.element[10].mapping[0].map","column":["a40"]},{"path":"StructureDefinition.differential.element[10].mapping[1].identity","column":["a41"]},{"path":"StructureDefinition.differential.element[10].mapping[1].map","column":["a42"]},{"path":"StructureDefinition.differential.element[10].mapping[2].identity","column":["a43"]},{"path":"StructureDefinition.differential.element[10].mapping[2].map","column":["a44"]},{"path":"StructureDefinition.differential.element[11].id","column":["a45"]},{"path":"StructureDefinition.differential.element[11].path","column":["a46"]},{"path":"StructureDefinition.differential.element[11].short","column":["a47"]},{"path":"StructureDefinition.differential.element[11].definition","column":["a48"]},{"path":"StructureDefinition.differential.element[11].min","column":["a49"]},{"path":"StructureDefinition.differential.element[11].max","column":["a50"]},{"path":"StructureDefinition.differential.element[11].type[0].code","column":["a51"]},{"path":"StructureDefinition.differential.element[11].type[0].targetProfile[0]","column":["a52"]},{"path":"StructureDefinition.differential.element[11].type[0].targetProfile[1]","column":["a53"]},{"path":"StructureDefinition.differential.element[11].type[0].targetProfile[2]","column":["a54"]},{"path":"StructureDefinition.differential.element[11].type[0].targetProfile[3]","column":["a55"]},{"path":"StructureDefinition.differential.element[11].type[0].targetProfile[4]","column":["a56"]},{"path":"StructureDefinition.differential.element[11].isSummary","column":["a57"]},{"path":"StructureDefinition.differential.element[11].mapping[0].identity","column":["a58"]},{"path":"StructureDefinition.differential.element[11].mapping[0].map","column":["a59"]},{"path":"StructureDefinition.differential.element[11].mapping[1].identity","column":["a60"]},{"path":"StructureDefinition.differential.element[11].mapping[1].map","column":["a61"]},{"path":"StructureDefinition.differential.element[11].mapping[2].identity","column":["a62"]},{"path":"StructureDefinition.differential.element[11].mapping[2].map","column":["a63"]},{"path":"StructureDefinition.differential.element[11].mapping[3].identity","column":["a64"]},{"path":"StructureDefinition.differential.element[11].mapping[3].map","column":["a65"]},{"path":"StructureDefinition.differential.element[12].id","column":["a66"]},{"path":"StructureDefinition.differential.element[12].path","column":["a67"]},{"path":"StructureDefinition.differential.element[12].short","column":["a68"]},{"path":"StructureDefinition.differential.element[12].definition","column":["a69"]},{"path":"StructureDefinition.differential.element[12].requirements","column":["a70"]},{"path":"StructureDefinition.differential.element[12].min","column":["a71"]},{"path":"StructureDefinition.differential.element[12].max","column":["a72"]},{"path":"StructureDefinition.differential.element[12].type[0].code","column":["a73"]},{"path":"StructureDefinition.differential.element[12].isSummary","column":["a74"]},{"path":"StructureDefinition.differential.element[12].binding.extension[0].url","column":["a75"]},{"path":"StructureDefinition.differential.element[12].binding.extension[0].valueString","column":["a76"]},{"path":"StructureDefinition.differential.element[12].binding.strength","column":["a77"]},{"path":"StructureDefinition.differential.element[12].binding.description","column":["a78"]},{"path":"StructureDefinition.differential.element[12].binding.valueSet","column":["a79"]},{"path":"StructureDefinition.differential.element[12].mapping[0].identity","column":["a80"]},{"path":"StructureDefinition.differential.element[12].mapping[0].map","column":["a81"]},{"path":"StructureDefinition.differential.element[12].mapping[1].identity","column":["a82"]},{"path":"StructureDefinition.differential.element[12].mapping[1].map","column":["a83"]},{"path":"StructureDefinition.differential.element[13].id","column":["a84"]},{"path":"StructureDefinition.differential.element[13].path","column":["a85"]},{"path":"StructureDefinition.differential.element[13].short","column":["a86"]},{"path":"StructureDefinition.differential.element[13].definition","column":["a87"]},{"path":"StructureDefinition.differential.element[13].min","column":["a88"]},{"path":"StructureDefinition.differential.element[13].max","column":["a89"]},{"path":"StructureDefinition.differential.element[13].type[0].code","column":["a90"]},{"path":"StructureDefinition.differential.element[13].mapping[0].identity","column":["a91"]},{"path":"StructureDefinition.differential.element[13].mapping[0].map","column":["a92"]},{"path":"StructureDefinition.differential.element[13].mapping[1].identity","column":["a93"]},{"path":"StructureDefinition.differential.element[13].mapping[1].map","column":["a94"]}]}]