[{"class":"MolecularSequence","view":{"query":"select * from a906600670_0"},"identifier":[{"path":"MolecularSequence","column":["_subject"]}],"mapping":[{"path":"MolecularSequence.id","function":"return 'graphic-example-2'"},{"path":"MolecularSequence.text.status","column":["a2"]},{"path":"MolecularSequence.text.div","column":["a3"]},{"path":"MolecularSequence.type","column":["a4"]},{"path":"MolecularSequence.coordinateSystem","column":["a5"]},{"path":"MolecularSequence.referenceSeq.referenceSeqString","function":"return getValue('a6').upper()","column":["a6"]},{"path":"MolecularSequence.referenceSeq.strand","column":["a7"]},{"path":"MolecularSequence.referenceSeq.windowStart","column":["a8"]},{"path":"MolecularSequence.referenceSeq.windowEnd","column":["a9"]},{"path":"MolecularSequence.pointer[0].reference","column":["a10"]},{"path":"MolecularSequence.meta.tag[0].system","column":["a11"]},{"path":"MolecularSequence.meta.tag[0].code","function":"return getValue('a12').upper()","column":["a12"]},{"path":"MolecularSequence.meta.tag[0].display","column":["a13"]}]}]